dlfast/ANN.py
dlfast/__init__.py
dlfast-0.0.1.dist-info/LICENSE
dlfast-0.0.1.dist-info/METADATA
dlfast-0.0.1.dist-info/WHEEL
dlfast-0.0.1.dist-info/top_level.txt
dlfast-0.0.1.dist-info/RECORD
